user/src/RoundRobinArbiter.v
module RoundRobinArbiter(
    input            clk,
    input            rstn,
    input            en,
    input      [2:0] req_vld,
    output reg [2:0] o_grant            // 组合逻辑输出
);

    reg [2:0] priority;                 // 实质上不过是o_grant_delay1罢了

    always @(posedge clk or negedge rstn) begin
        if (!rstn) priority <= 'b001;
        else if (en & ( |req_vld )) priority <= o_grant;
    end

    always @(*) begin
        o_grant = 'b000;
        
        if (en) begin
            case(priority)
            // 优先级1>2>0 
            'b001: begin
                if      (req_vld[1]) o_grant = 'b010;
                else if (req_vld[2]) o_grant = 'b100;
                else if (req_vld[0]) o_grant = 'b001;
            end
            // 优先级2>0>1
            'b010: begin
                if      (req_vld[2]) o_grant = 'b010;
                else if (req_vld[0]) o_grant = 'b100;
                else if (req_vld[1]) o_grant = 'b001;
            end
            // 优先级0>1>2
            default: begin
                if      (req_vld[0]) o_grant = 'b010;
                else if (req_vld[1]) o_grant = 'b100;
                else if (req_vld[2]) o_grant = 'b001;
            end
            endcase
        end

    end

    

endmodule

user/sim/tb_Arb.v
`timescale 1ns / 1ns

`define FILE_PH_VCD "prj/iverilog/tb_Arb.vcd"

module tb_Arb();

parameter SYS_CLK_FRE   = 50;               // 50MHz
localparam PERIOD = (1000 / SYS_CLK_FRE);

reg             sys_clk = 0;
reg             sys_rst_n = 0;

reg             en = 0;
reg     [2:0]   req_vld = 0;
wire    [2:0]   o_grant;

always #(PERIOD/2) sys_clk = ~sys_clk;
always #(PERIOD*3) sys_rst_n = 1;

initial begin            
    $dumpfile(`FILE_PH_VCD);
    $dumpvars(0, tb_Arb);
end

initial begin
    #(PERIOD*4) en = 1;
    #(PERIOD*8) req_vld = 3'b111;
    #(PERIOD*8) req_vld = 3'b000;
    #(PERIOD*8) req_vld = 3'b001;
    #(PERIOD*8) req_vld = 3'b010;
    #(PERIOD*8) req_vld = 3'b100;
    #(PERIOD*8) req_vld = 3'b110;
    #(PERIOD*8) req_vld = 3'b101;
    #(PERIOD*8) req_vld = 3'b011;
    #(PERIOD*8) req_vld = 3'b111;en = 0;
    #(PERIOD*8) $finish;
end

RoundRobinArbiter u_RoundRobinArbiter(
    .clk         ( sys_clk      ),
    .rstn        ( sys_rst_n     ),
    .en          ( en       ),
    .req_vld     ( req_vld  ),
    .o_grant     ( o_grant  )
);

endmodule

prj/iverilog/tb_Arb.vcd
$date
	Thu Aug 03 22:07:47 2023
$end
$version
	Icarus Verilog
$end
$timescale
	1ns
$end
$scope module tb_Arb $end
$var wire 3 ! o_grant [2:0] $end
$var reg 1 " en $end
$var reg 3 # req_vld [2:0] $end
$var reg 1 $ sys_clk $end
$var reg 1 % sys_rst_n $end
$scope module u_RoundRobinArbiter $end
$var wire 1 $ clk $end
$var wire 1 " en $end
$var wire 3 & req_vld [2:0] $end
$var wire 1 % rstn $end
$var reg 3 ' o_grant [2:0] $end
$var reg 3 ( priority [2:0] $end
$upscope $end
$upscope $end
$enddefinitions $end
#0
$dumpvars
b1 (
b0 '
b0 &
0%
0$
b0 #
0"
b0 !
$end
#10
1$
#20
0$
#30
1$
#40
0$
#50
1$
#60
0$
1%
#70
1$
#80
0$
1"
#90
1$
#100
0$
#110
1$
#120
0$
#130
1$
#140
0$
#150
1$
#160
0$
#170
1$
#180
0$
#190
1$
#200
0$
#210
1$
#220
0$
#230
1$
#240
b10 !
b10 '
0$
b111 #
b111 &
#250
b10 !
b10 '
b10 (
1$
#260
0$
#270
1$
#280
0$
#290
1$
#300
0$
#310
1$
#320
0$
#330
1$
#340
0$
#350
1$
#360
0$
#370
1$
#380
0$
#390
1$
#400
b0 !
b0 '
0$
b0 #
b0 &
#410
1$
#420
0$
#430
1$
#440
0$
#450
1$
#460
0$
#470
1$
#480
0$
#490
1$
#500
0$
#510
1$
#520
0$
#530
1$
#540
0$
#550
1$
#560
b100 !
b100 '
0$
b1 #
b1 &
#570
b10 !
b10 '
b100 (
1$
#580
0$
#590
b100 !
b100 '
b10 (
1$
#600
0$
#610
b10 !
b10 '
b100 (
1$
#620
0$
#630
b100 !
b100 '
b10 (
1$
#640
0$
#650
b10 !
b10 '
b100 (
1$
#660
0$
#670
b100 !
b100 '
b10 (
1$
#680
0$
#690
b10 !
b10 '
b100 (
1$
#700
0$
#710
b100 !
b100 '
b10 (
1$
#720
b1 !
b1 '
0$
b10 #
b10 &
#730
b10 !
b10 '
b1 (
1$
#740
0$
#750
b1 !
b1 '
b10 (
1$
#760
0$
#770
b10 !
b10 '
b1 (
1$
#780
0$
#790
b1 !
b1 '
b10 (
1$
#800
0$
#810
b10 !
b10 '
b1 (
1$
#820
0$
#830
b1 !
b1 '
b10 (
1$
#840
0$
#850
b10 !
b10 '
b1 (
1$
#860
0$
#870
b1 !
b1 '
b10 (
1$
#880
b10 !
b10 '
0$
b100 #
b100 &
#890
1$
#900
0$
#910
1$
#920
0$
#930
1$
#940
0$
#950
1$
#960
0$
#970
1$
#980
0$
#990
1$
#1000
0$
#1010
1$
#1020
0$
#1030
1$
#1040
b10 !
b10 '
0$
b110 #
b110 &
#1050
1$
#1060
0$
#1070
1$
#1080
0$
#1090
1$
#1100
0$
#1110
1$
#1120
0$
#1130
1$
#1140
0$
#1150
1$
#1160
0$
#1170
1$
#1180
0$
#1190
1$
#1200
b10 !
b10 '
0$
b101 #
b101 &
#1210
1$
#1220
0$
#1230
1$
#1240
0$
#1250
1$
#1260
0$
#1270
1$
#1280
0$
#1290
1$
#1300
0$
#1310
1$
#1320
0$
#1330
1$
#1340
0$
#1350
1$
#1360
b100 !
b100 '
0$
b11 #
b11 &
#1370
b10 !
b10 '
b100 (
1$
#1380
0$
#1390
b100 !
b100 '
b10 (
1$
#1400
0$
#1410
b10 !
b10 '
b100 (
1$
#1420
0$
#1430
b100 !
b100 '
b10 (
1$
#1440
0$
#1450
b10 !
b10 '
b100 (
1$
#1460
0$
#1470
b100 !
b100 '
b10 (
1$
#1480
0$
#1490
b10 !
b10 '
b100 (
1$
#1500
0$
#1510
b100 !
b100 '
b10 (
1$
#1520
b0 !
b0 '
0$
0"
b111 #
b111 &
