user/src/RoundRobinArbiter.v
// 公平轮转仲裁器
// 输入端口: clk, rstn, en, req_vld[2:0]
// 输出端口: o_grant[2:0]

module RoundRobinArbiter(
    input wire clk,
    input wire rstn,
    input wire en,
    input wire [2:0] req_vld,
    output reg [2:0] o_grant
);

reg [2:0] last_grant;           // 上一clk的优先级

always @(posedge clk) begin
    if (en) begin
        case (last_grant)
            'b001: begin
                if      (req_vld[0]) o_grant <= 3'b001;
                else if (req_vld[1]) o_grant <= 3'b010;
                else if (req_vld[2]) o_grant <= 3'b100;
                else                 o_grant <= 3'b000;
            end
            'b010: begin
                if      (req_vld[1]) o_grant <= 3'b010;
                else if (req_vld[2]) o_grant <= 3'b100;
                else if (req_vld[0]) o_grant <= 3'b001;
                else                 o_grant <= 3'b000;
            end
            'b100: begin
                if      (req_vld[2]) o_grant <= 3'b100;
                else if (req_vld[0]) o_grant <= 3'b001;
                else if (req_vld[1]) o_grant <= 3'b010;
                else                 o_grant <= 3'b000;
            end
            default: o_grant <= 3'b000;
        endcase
    end
    else
        o_grant <= 3'b000;
end

// last_grant
always @(posedge clk or negedge rstn) begin
    if (!rstn) last_grant <= 'b001;
    else if (en) begin
        if (o_grant[0])
            last_grant <= 'b001;
        else if (o_grant[1])
            last_grant <= 'b010;
        else if (o_grant[2])
            last_grant <= 'b100;
    end
end

endmodule

user/sim/tb_Arb.v
`timescale 1ns / 1ns

`define FILE_PH_VCD "prj/iverilog/tb_Arb.vcd"

module tb_Arb();

parameter SYS_CLK_FRE   = 50;               // 50MHz
localparam PERIOD = (1000 / SYS_CLK_FRE);

reg             sys_clk = 1;
reg             sys_rst_n = 0;

reg             en = 0;
reg     [2:0]   req_vld = 0;
wire    [2:0]   o_grant;

always #(PERIOD/2) sys_clk = ~sys_clk;
always #(PERIOD*2 + PERIOD/2) sys_rst_n = 1;

initial begin            
    $dumpfile(`FILE_PH_VCD);
    $dumpvars(0, tb_Arb);
end

initial begin
    #1;
    #(PERIOD*4) en = 1;
    #(PERIOD*2) req_vld = 3'b111;
    #(PERIOD*8) req_vld = 3'b000;
    #(PERIOD*8) req_vld = 3'b001;
    #(PERIOD*8) req_vld = 3'b110;
    #(PERIOD*8) req_vld = 3'b011;
    #(PERIOD*8) req_vld = 3'b101;
    #(PERIOD*8) req_vld = 3'b011;
    #(PERIOD*8) req_vld = 3'b111;en = 0;
    #(PERIOD*8) $finish;
end

RoundRobinArbiter u_Arb(
    .clk         ( sys_clk      ),
    .rstn        ( sys_rst_n    ),
    .en          ( en           ),
    .req_vld     ( req_vld      ),
    .o_grant     ( o_grant      )
);

endmodule

prj/iverilog/tb_Arb.vcd
$date
	Thu Aug 03 23:10:58 2023
$end
$version
	Icarus Verilog
$end
$timescale
	1ns
$end
$scope module tb_Arb $end
$var wire 3 ! o_grant [2:0] $end
$var reg 1 " en $end
$var reg 3 # req_vld [2:0] $end
$var reg 1 $ sys_clk $end
$var reg 1 % sys_rst_n $end
$scope module u_Arb $end
$var wire 1 $ clk $end
$var wire 1 " en $end
$var wire 3 & req_vld [2:0] $end
$var wire 1 % rstn $end
$var reg 3 ' last_grant [2:0] $end
$var reg 3 ( o_grant [2:0] $end
$upscope $end
$upscope $end
$enddefinitions $end
#0
$dumpvars
b0 (
b1 '
b0 &
0%
1$
b0 #
0"
b0 !
$end
#10
0$
#20
1$
#30
0$
#40
1$
#50
0$
1%
#60
1$
#70
0$
#80
1$
#81
1"
#90
0$
#100
1$
#110
0$
#120
1$
#121
b111 #
b111 &
#130
0$
#140
b1 !
b1 (
1$
#150
0$
#160
1$
#170
0$
#180
1$
#190
0$
#200
1$
#210
0$
#220
1$
#230
0$
#240
1$
#250
0$
#260
1$
#270
0$
#280
1$
#281
b0 #
b0 &
#290
0$
#300
b0 !
b0 (
1$
#310
0$
#320
1$
#330
0$
#340
1$
#350
0$
#360
1$
#370
0$
#380
1$
#390
0$
#400
1$
#410
0$
#420
1$
#430
0$
#440
1$
#441
b1 #
b1 &
#450
0$
#460
b1 !
b1 (
1$
#470
0$
#480
1$
#490
0$
#500
1$
#510
0$
#520
1$
#530
0$
#540
1$
#550
0$
#560
1$
#570
0$
#580
1$
#590
0$
#600
1$
#601
b110 #
b110 &
#610
0$
#620
b10 !
b10 (
1$
#630
0$
#640
b10 '
1$
#650
0$
#660
1$
#670
0$
#680
1$
#690
0$
#700
1$
#710
0$
#720
1$
#730
0$
#740
1$
#750
0$
#760
1$
#761
b11 #
b11 &
#770
0$
#780
1$
#790
0$
#800
1$
#810
0$
#820
1$
#830
0$
#840
1$
#850
0$
#860
1$
#870
0$
#880
1$
#890
0$
#900
1$
#910
0$
#920
1$
#921
b101 #
b101 &
#930
0$
#940
b100 !
b100 (
1$
#950
0$
#960
b100 '
1$
#970
0$
#980
1$
#990
0$
#1000
1$
#1010
0$
#1020
1$
#1030
0$
#1040
1$
#1050
0$
#1060
1$
#1070
0$
#1080
1$
#1081
b11 #
b11 &
#1090
0$
#1100
b1 !
b1 (
1$
#1110
0$
#1120
b1 '
1$
#1130
0$
#1140
1$
#1150
0$
#1160
1$
#1170
0$
#1180
1$
#1190
0$
#1200
1$
#1210
0$
#1220
1$
#1230
0$
#1240
1$
#1241
0"
b111 #
b111 &
#1250
0$
#1260
b0 !
b0 (
1$
